termr/__init__.py
termr/api.py
termr/config.py
termr/favorites.py
termr/main.py
termr/models.py
termr/player.py
termr/termr.css
termr/themes.py
termr/ui.py
termr/version.py
termr-1.2.0.data/data/share/man/man1/termr.1
termr-1.2.0.dist-info/licenses/LICENSE
termr-1.2.0.dist-info/METADATA
termr-1.2.0.dist-info/WHEEL
termr-1.2.0.dist-info/entry_points.txt
termr-1.2.0.dist-info/top_level.txt
termr-1.2.0.dist-info/RECORD
