Metadata-Version: 2.4
Name: termr
Version: 1.2.0
Summary: Terminal-based radio player with TUI
Home-page: https://github.com/Hibbins/termr
Author: Sebastian Westberg
Author-email: Sebastian Westberg <sebastian@westberg.io>
License-Expression: MIT
Project-URL: Homepage, https://github.com/Hibbins/termr
Project-URL: Repository, https://github.com/Hibbins/termr
Project-URL: Issues, https://github.com/Hibbins/termr/issues
Project-URL: Documentation, https://github.com/Hibbins/termr#readme
Keywords: radio,terminal,tui,music,streaming
Classifier: Development Status :: 5 - Production/Stable
Classifier: Environment :: Console :: Curses
Classifier: Intended Audience :: End Users/Desktop
Classifier: Operating System :: OS Independent
Classifier: Programming Language :: Python :: 3
Classifier: Programming Language :: Python :: 3.10
Classifier: Programming Language :: Python :: 3.11
Classifier: Programming Language :: Python :: 3.12
Classifier: Topic :: Multimedia :: Sound/Audio :: Players
Classifier: Topic :: Internet :: WWW/HTTP :: Dynamic Content
Classifier: Topic :: Utilities
Requires-Python: >=3.10
License-File: LICENSE
Requires-Dist: textual>=0.40.0
Requires-Dist: requests>=2.31.0
Requires-Dist: rich>=13.0.0
Dynamic: author
Dynamic: home-page
Dynamic: license-file
Dynamic: requires-python
